{
"nodes":[
{ "name":"Aloísio José Bueno Cotta", "idlattes":"3298545143757892", "rotulo":"[Sem rotulo]", "collaborationrank":1.0628372430801392 },
{ "name":"Ana Nery Furlan Mendes", "idlattes":"8266113579775016", "rotulo":"[Sem rotulo]", "collaborationrank":1.8013333082199097 },
{ "name":"Ana Paula Oliveira Costa", "idlattes":"0380297522790929", "rotulo":"[Sem rotulo]", "collaborationrank":0.4941891133785248 },
{ "name":"Andre Gonçalves de Lima", "idlattes":"4496654673061366", "rotulo":"[Sem rotulo]", "collaborationrank":0.15000000596046448 },
{ "name":"Andre Luíz Alves", "idlattes":"5320330508972933", "rotulo":"[Sem rotulo]", "collaborationrank":1.3285188674926758 },
{ "name":"Breno Nonato de Melo", "idlattes":"3410912882231783", "rotulo":"[Sem rotulo]", "collaborationrank":0.31837472319602966 },
{ "name":"Carla da Silva Meireles", "idlattes":"9685470701740945", "rotulo":"[Sem rotulo]", "collaborationrank":1.782791256904602 },
{ "name":"Carlos André Maximiano da Silva", "idlattes":"6667248292479031", "rotulo":"[Sem rotulo]", "collaborationrank":0.15000000596046448 },
{ "name":"Christiane Mapheu Nogueira", "idlattes":"2522406207908377", "rotulo":"[Sem rotulo]", "collaborationrank":1.1801819801330566 },
{ "name":"Débora Pereira Araujo", "idlattes":"9664531819814847", "rotulo":"[Sem rotulo]", "collaborationrank":0.7652045488357544 },
{ "name":"Eduardo Perini Muniz", "idlattes":"8285018770645807", "rotulo":"[Sem rotulo]", "collaborationrank":0.6035908460617065 },
{ "name":"George Ricardo Santana Andrade", "idlattes":"1419428893704446", "rotulo":"[Sem rotulo]", "collaborationrank":1.1646263599395752 },
{ "name":"Gilmene Bianco", "idlattes":"0111900440522917", "rotulo":"[Sem rotulo]", "collaborationrank":0.320125937461853 },
{ "name":"Gustavo Viali Loyola", "idlattes":"6464661567161861", "rotulo":"[Sem rotulo]", "collaborationrank":0.7504248023033142 },
{ "name":"Jefferson Lima Fernandes André", "idlattes":"6632598745671715", "rotulo":"[Sem rotulo]", "collaborationrank":0.15000000596046448 },
{ "name":"José André Lourenço", "idlattes":"2699117520955351", "rotulo":"[Sem rotulo]", "collaborationrank":0.15000000596046448 },
{ "name":"Luiz Gabriel Souza de Oliveira", "idlattes":"5722300748929381", "rotulo":"[Sem rotulo]", "collaborationrank":1.0 },
{ "name":"Luiz Gustavo Ferreira Soares", "idlattes":"4517059757920195", "rotulo":"[Sem rotulo]", "collaborationrank":0.15000000596046448 },
{ "name":"Marcia Helena Rodrigues Velloso", "idlattes":"9991164750729669", "rotulo":"[Sem rotulo]", "collaborationrank":1.2508430480957031 },
{ "name":"Marcio Solino Pessoa", "idlattes":"2752782453011955", "rotulo":"[Sem rotulo]", "collaborationrank":1.0685540437698364 },
{ "name":"Maria de Fatima Pereira dos Santos", "idlattes":"0376041929696875", "rotulo":"[Sem rotulo]", "collaborationrank":1.5106757879257202 },
{ "name":"Mariléa Gomes dos Santos Ribeiro", "idlattes":"6838038881434963", "rotulo":"[Sem rotulo]", "collaborationrank":0.15000000596046448 },
{ "name":"Maristela de Araujo Vicente", "idlattes":"1832685910267156", "rotulo":"[Sem rotulo]", "collaborationrank":1.4172378778457642 },
{ "name":"Mellina Damasceno Rachid Santos", "idlattes":"9434564411683567", "rotulo":"[Sem rotulo]", "collaborationrank":0.872729480266571 },
{ "name":"Natália Valadares", "idlattes":"3689867487273875", "rotulo":"[Sem rotulo]", "collaborationrank":1.0 },
{ "name":"Paulo Sérgio Moscon", "idlattes":"0422485640031962", "rotulo":"[Sem rotulo]", "collaborationrank":0.9451249837875366 },
{ "name":"Raniella Falchetto Bazoni", "idlattes":"3349837205962461", "rotulo":"[Sem rotulo]", "collaborationrank":0.15000000596046448 },
{ "name":"Raphael Góes Furtado", "idlattes":"7034365539639197", "rotulo":"[Sem rotulo]", "collaborationrank":0.15000000596046448 },
{ "name":"Ricardo Lopes da Silva", "idlattes":"2598314759854581", "rotulo":"[Sem rotulo]", "collaborationrank":1.0 },
{ "name":"Rodrigo da Costa Silva", "idlattes":"7120418895468591", "rotulo":"[Sem rotulo]", "collaborationrank":1.0 },
{ "name":"Rodrigo Dias Pereira", "idlattes":"3414799692619699", "rotulo":"[Sem rotulo]", "collaborationrank":0.6946191787719727 },
{ "name":"Thonimar Vieira de Alencar Souza", "idlattes":"6095468454824366", "rotulo":"[Sem rotulo]", "collaborationrank":0.15000000596046448 },
{ "name":"Vivian Chagas da Silveira", "idlattes":"0811158352700883", "rotulo":"[Sem rotulo]", "collaborationrank":0.6680167317390442 }
],
"links":[
{ "source":0, "target":10, "value":1.0 },
{ "source":0, "target":23, "value":4.0 },
{ "source":1, "target":2, "value":2.0 },
{ "source":1, "target":6, "value":5.0 },
{ "source":1, "target":8, "value":2.0 },
{ "source":1, "target":11, "value":4.0 },
{ "source":1, "target":12, "value":1.0 },
{ "source":1, "target":32, "value":1.0 },
{ "source":2, "target":8, "value":2.0 },
{ "source":2, "target":32, "value":1.0 },
{ "source":4, "target":13, "value":5.0 },
{ "source":4, "target":18, "value":1.0 },
{ "source":4, "target":19, "value":7.0 },
{ "source":4, "target":20, "value":2.0 },
{ "source":4, "target":22, "value":1.0 },
{ "source":4, "target":25, "value":6.0 },
{ "source":4, "target":30, "value":2.0 },
{ "source":5, "target":6, "value":1.0 },
{ "source":6, "target":11, "value":5.0 },
{ "source":6, "target":32, "value":1.0 },
{ "source":8, "target":9, "value":1.0 },
{ "source":8, "target":18, "value":3.0 },
{ "source":8, "target":32, "value":2.0 },
{ "source":9, "target":18, "value":4.0 },
{ "source":10, "target":19, "value":1.0 },
{ "source":10, "target":25, "value":1.0 },
{ "source":10, "target":30, "value":2.0 },
{ "source":13, "target":19, "value":2.0 },
{ "source":13, "target":25, "value":1.0 },
{ "source":13, "target":30, "value":2.0 },
{ "source":16, "target":24, "value":2.0 },
{ "source":18, "target":19, "value":1.0 },
{ "source":18, "target":25, "value":1.0 },
{ "source":19, "target":20, "value":2.0 },
{ "source":19, "target":22, "value":1.0 },
{ "source":19, "target":25, "value":7.0 },
{ "source":19, "target":30, "value":1.0 },
{ "source":20, "target":22, "value":21.0 },
{ "source":20, "target":25, "value":2.0 },
{ "source":22, "target":25, "value":1.0 },
{ "source":25, "target":30, "value":1.0 },
{ "source":28, "target":29, "value":21.0 }
]
}